turbo_allauth/__init__.py
turbo_allauth/apps.py
turbo_allauth/urls.py
turbo_allauth/views/__init__.py
turbo_allauth/views/account.py
turbo_allauth/views/socialaccount.py
django_turbo_allauth-0.0.10.dist-info/LICENSE
django_turbo_allauth-0.0.10.dist-info/METADATA
django_turbo_allauth-0.0.10.dist-info/WHEEL
django_turbo_allauth-0.0.10.dist-info/top_level.txt
django_turbo_allauth-0.0.10.dist-info/RECORD
