Metadata-Version: 2.1
Name: django-turbo-allauth
Version: 0.0.10
Summary: Hotwired/Turbo subclasses for allauth views
Home-page: https://github.com/hotwire-django/django-turbo-allauth
Author: Dan Jacob
Author-email: danjac2018@gmail.com
License: MIT
Platform: UNKNOWN
Classifier: Development Status :: 4 - Beta
Classifier: Framework :: Django
Classifier: Intended Audience :: Developers
Classifier: License :: OSI Approved :: MIT License
Classifier: Programming Language :: Python
Classifier: Programming Language :: Python :: 3.8
Classifier: Programming Language :: Python :: 3.9
Classifier: Topic :: Software Development :: Libraries :: Python Modules
Requires-Python: >=3.8
Requires-Dist: django (>=3.0)
Requires-Dist: django-allauth
Requires-Dist: django-turbo-response (>=0.0.49)
